HoloViro/HoloViro.py
HoloViro/__init__.py
holoviro-0.1.6.dist-info/licenses/LICENSE
holoviro-0.1.6.dist-info/licenses/NOTICE
holoviro-0.1.6.dist-info/METADATA
holoviro-0.1.6.dist-info/WHEEL
holoviro-0.1.6.dist-info/top_level.txt
holoviro-0.1.6.dist-info/RECORD
