Metadata-Version: 2.4
Name: HoloViro
Version: 0.1.6
Summary: Thread-safe, singleton virtual environment manager for rapid code generation, safe pip installs, and sandboxed Python automation.
Author: Tristan McBride Sr.
Author-email: "Tristan McBride Sr." <142635792+TristanMcBrideSr@users.noreply.github.com>
Project-URL: Homepage, https://github.com/TristanMcBrideSr
Requires-Python: >=3.10
License-File: LICENSE
License-File: NOTICE
Requires-Dist: pyperclip
Requires-Dist: pyautogui
Requires-Dist: python-dotenv
Requires-Dist: uv
Dynamic: author
Dynamic: license-file
